sysnet_pdf/__init__.py
sysnet_pdf/config.py
sysnet_pdf/jasper.py
sysnet_pdf/pdf_utils.py
sysnet_pdffiller-1.3.1.dist-info/licenses/LICENSE
sysnet_pdffiller-1.3.1.dist-info/METADATA
sysnet_pdffiller-1.3.1.dist-info/WHEEL
sysnet_pdffiller-1.3.1.dist-info/top_level.txt
sysnet_pdffiller-1.3.1.dist-info/RECORD
