Metadata-Version: 2.4
Name: sysnet-pdffiller
Version: 1.3.1
Summary: Tools for filling PDF templates with data
Author-email: Data Developer <info@sysnet.cz>
Project-URL: Homepage, https://github.com/SYSNET-CZ/pdf/tree/master/pdf-filler
Classifier: Development Status :: 5 - Production/Stable
Classifier: Programming Language :: Python :: 3
Classifier: Intended Audience :: Developers
Classifier: License :: Free For Home Use
Classifier: Natural Language :: Czech
Classifier: Operating System :: OS Independent
Classifier: Topic :: Software Development :: Libraries
Requires-Python: >=3.9
License-File: LICENSE
Requires-Dist: pypdf>=6.1.1
Requires-Dist: fillpdf==0.7.3
Requires-Dist: pyreportjasper~=2.1.4
Requires-Dist: sysnet-pyutils>=1.0.7
Dynamic: license-file
